{"namedChunkGroups":{"polyfill":{"name":"polyfill","assets":[{"name":"webpack-runtime-c1f0e499abd694e8d335.js","size":5072},{"name":"polyfill-e7fd2f565a857dc57935.js","size":82650}],"filteredAssets":0,"assetsSize":87722,"filteredAuxiliaryAssets":2,"auxiliaryAssetsSize":221416},"app":{"name":"app","assets":[{"name":"webpack-runtime-c1f0e499abd694e8d335.js","size":5072},{"name":"framework-89ddeb149991009fa125.js","size":128977},{"name":"app-9c94ec82ee95aa8d7717.js","size":68488}],"filteredAssets":0,"assetsSize":202537,"filteredAuxiliaryAssets":3,"auxiliaryAssetsSize":651444},"component---src-pages-404-js":{"name":"component---src-pages-404-js","assets":[{"name":"styles.ac46d673741bae581fd4.css","size":5384},{"name":"commons-4a618a8fb50b4861a7f2.js","size":16807},{"name":"component---src-pages-404-js-614c237d7296d0d174a8.js","size":485}],"filteredAssets":0,"assetsSize":22676,"filteredAuxiliaryAssets":2,"auxiliaryAssetsSize":70311},"component---src-pages-index-js":{"name":"component---src-pages-index-js","assets":[{"name":"styles.ac46d673741bae581fd4.css","size":5384},{"name":"commons-4a618a8fb50b4861a7f2.js","size":16807},{"name":"component---src-pages-index-js-0abbd974ba4436814e5f.js","size":397}],"filteredAssets":0,"assetsSize":22588,"filteredAuxiliaryAssets":2,"auxiliaryAssetsSize":70253},"component---src-pages-page-2-js":{"name":"component---src-pages-page-2-js","assets":[{"name":"styles.ac46d673741bae581fd4.css","size":5384},{"name":"commons-4a618a8fb50b4861a7f2.js","size":16807},{"name":"component---src-pages-page-2-js-cc474c12301b61c144f1.js","size":522}],"filteredAssets":0,"assetsSize":22713,"filteredAuxiliaryAssets":2,"auxiliaryAssetsSize":70408},"component---src-pages-using-typescript-tsx":{"name":"component---src-pages-using-typescript-tsx","assets":[{"name":"styles.ac46d673741bae581fd4.css","size":5384},{"name":"commons-4a618a8fb50b4861a7f2.js","size":16807},{"name":"component---src-pages-using-typescript-tsx-127fa5e1e20f779b80d7.js","size":1333}],"filteredAssets":0,"assetsSize":23524,"filteredAuxiliaryAssets":2,"auxiliaryAssetsSize":71731}},"assetsByChunkName":{"polyfill":["webpack-runtime-c1f0e499abd694e8d335.js","polyfill-e7fd2f565a857dc57935.js"],"app":["webpack-runtime-c1f0e499abd694e8d335.js","framework-89ddeb149991009fa125.js","app-9c94ec82ee95aa8d7717.js"],"component---src-pages-404-js":["styles.ac46d673741bae581fd4.css","commons-4a618a8fb50b4861a7f2.js","component---src-pages-404-js-614c237d7296d0d174a8.js"],"component---src-pages-index-js":["styles.ac46d673741bae581fd4.css","commons-4a618a8fb50b4861a7f2.js","component---src-pages-index-js-0abbd974ba4436814e5f.js"],"component---src-pages-page-2-js":["styles.ac46d673741bae581fd4.css","commons-4a618a8fb50b4861a7f2.js","component---src-pages-page-2-js-cc474c12301b61c144f1.js"],"component---src-pages-using-typescript-tsx":["styles.ac46d673741bae581fd4.css","commons-4a618a8fb50b4861a7f2.js","component---src-pages-using-typescript-tsx-127fa5e1e20f779b80d7.js"]},"childAssetsByChunkName":{}}